src/sciplot/__init__.py
src/sciplot/sciplot.py
diego_plot-1.0.dist-info/METADATA
diego_plot-1.0.dist-info/WHEEL
diego_plot-1.0.dist-info/licenses/LICENSE
diego_plot-1.0.dist-info/RECORD
