Metadata-Version: 2.1
Name: diego-plot
Version: 1.0
Summary: A scientific style plot tool based on matplotlib.
Project-URL: Homepage, https://github.com/caikaidi/sciplot
Project-URL: Bug Tracker, https://github.com/caikaidi/sciplot/issues
Author-email: diego <caikaidi@caikaidi.cn>
License-File: LICENSE
Classifier: License :: OSI Approved :: MIT License
Classifier: Operating System :: OS Independent
Classifier: Programming Language :: Python :: 3
Requires-Python: >=3.7
Requires-Dist: cycler
Requires-Dist: matplotlib
Requires-Dist: numpy
